LICENSE
MANIFEST.in
README.rst
setup.cfg
setup.py
consulate/__init__.py
consulate/adapters.py
consulate/cli.py
consulate/client.py
consulate/exceptions.py
consulate/utils.py
consulate/api/__init__.py
consulate/api/acl.py
consulate/api/agent.py
consulate/api/base.py
consulate/api/catalog.py
consulate/api/coordinate.py
consulate/api/event.py
consulate/api/health.py
consulate/api/kv.py
consulate/api/lock.py
consulate/api/session.py
consulate/api/status.py
consulate/models/__init__.py
consulate/models/acl.py
consulate/models/agent.py
consulate/models/base.py
py_consulate_ms.egg-info/PKG-INFO
py_consulate_ms.egg-info/SOURCES.txt
py_consulate_ms.egg-info/dependency_links.txt
py_consulate_ms.egg-info/entry_points.txt
py_consulate_ms.egg-info/requires.txt
py_consulate_ms.egg-info/top_level.txt
py_consulate_ms.egg-info/zip-safe