Metadata-Version: 2.1
Name: py-consulate-ms
Version: 1.0.0
Summary: A Client library and command line application for the Consul
Home-page: https://consulate.readthedocs.org
Author: Gavin M. Roy
Author-email: gavinr@aweber.com
Maintainer: Lucas Ollarce
Maintainer-email: luk5ollarce@gmail.com
License: BSD
Classifier: Development Status :: 5 - Production/Stable
Classifier: Intended Audience :: Developers
Classifier: License :: OSI Approved :: BSD License
Classifier: Operating System :: OS Independent
Classifier: Programming Language :: Python :: 2
Classifier: Programming Language :: Python :: 2.7
Classifier: Programming Language :: Python :: 3
Classifier: Programming Language :: Python :: 3.3
Classifier: Programming Language :: Python :: 3.4
Classifier: Programming Language :: Python :: 3.5
Classifier: Programming Language :: Python :: 3.6
Classifier: Programming Language :: Python :: Implementation :: CPython
Classifier: Programming Language :: Python :: Implementation :: PyPy
Classifier: Topic :: System :: Systems Administration
Classifier: Topic :: System :: Clustering
Classifier: Topic :: Internet :: WWW/HTTP
Classifier: Topic :: Software Development :: Libraries
Provides-Extra: unixsocket
Provides-Extra: tests
License-File: LICENSE
